Metadata-Version: 2.1
Name: opendap-protocol
Version: 1.0.5
Summary: A pure Python implementation of the OPeNDAP server protocol.
Home-page: https://github.com/MeteoSwiss/opendap-protocol
Author: Philipp Falke
Author-email: philipp.falke@meteoswiss.ch
License: BSD-3-Clause license
Keywords: opendap_protocol
Platform: UNKNOWN
Classifier: Development Status :: 4 - Beta
Classifier: Intended Audience :: Developers
Classifier: License :: OSI Approved :: BSD License
Classifier: Natural Language :: English
Classifier: Programming Language :: Python :: 3.6
Classifier: Programming Language :: Python :: 3.7
Classifier: Programming Language :: Python :: 3.8
Provides-Extra: test
